README.md
setup.py
gluonar/__init__.py
gluonar/loss.py
gluonar.egg-info/PKG-INFO
gluonar.egg-info/SOURCES.txt
gluonar.egg-info/dependency_links.txt
gluonar.egg-info/requires.txt
gluonar.egg-info/top_level.txt
gluonar.egg-info/zip-safe
gluonar/data/__init__.py
gluonar/data/dataset.py
gluonar/data/transform.py
gluonar/metrics/__init__.py
gluonar/model_zoo/__init__.py
gluonar/model_zoo/resnet_sr.py
gluonar/nn/__init__.py
gluonar/nn/basic_blocks.py
gluonar/utils/__init__.py
gluonar/utils/viz.py
tests/unittests/__init__.py
tests/unittests/test_basic_blocks.py
tests/unittests/test_data.py