Metadata-Version: 2.1
Name: gluonar
Version: 0.1.0
Summary: Gluon Audio Toolkit
Home-page: https://github.com/haoxintong/gluon-audio
Author: haoxintong
Author-email: haoxintongpku@gmail.com
License: MIT
Platform: UNKNOWN
